mkdocs_techdocs_diamond/__init__.py
mkdocs_techdocs_diamond/_version.py
mkdocs_techdocs_diamond/config.yml
mkdocs_techdocs_diamond/plugin.py
mkdocs_techdocs_diamond-1.0.2.dist-info/LICENSE
mkdocs_techdocs_diamond-1.0.2.dist-info/METADATA
mkdocs_techdocs_diamond-1.0.2.dist-info/WHEEL
mkdocs_techdocs_diamond-1.0.2.dist-info/entry_points.txt
mkdocs_techdocs_diamond-1.0.2.dist-info/top_level.txt
mkdocs_techdocs_diamond-1.0.2.dist-info/RECORD
