Metadata-Version: 2.1
Name: mkdocs-techdocs-diamond
Version: 1.0.2
Summary: An Mkdocs plugin for configuring Diamond Techdocs sites
Author-email: Garry O'Donnell <garry.o'donnell@diamond.ac.uk>
License: Apache License
Project-URL: GitHub, https://github.com/DiamondLightSource/mkdocs-techdocs-diamond
Classifier: Development Status :: 3 - Alpha
Classifier: License :: OSI Approved :: Apache Software License
Classifier: Programming Language :: Python :: 3.9
Classifier: Programming Language :: Python :: 3.10
Classifier: Programming Language :: Python :: 3.11
Classifier: Programming Language :: Python :: 3.12
Requires-Python: >=3.9
License-File: LICENSE
Requires-Dist: mkdocs <1.6.0
Requires-Dist: mkdocs-awesome-pages-plugin
Requires-Dist: mkdocs-include-markdown-plugin
Requires-Dist: mkdocs-material
Requires-Dist: mdx-truly-sane-lists
Requires-Dist: pymdown-extensions
Requires-Dist: pygments
Provides-Extra: dev
Requires-Dist: black ; extra == 'dev'
Requires-Dist: mypy ; extra == 'dev'
Requires-Dist: pipdeptree ; extra == 'dev'
Requires-Dist: pre-commit ; extra == 'dev'
Requires-Dist: pytest ; extra == 'dev'
Requires-Dist: pytest-cov ; extra == 'dev'
Requires-Dist: ruff ; extra == 'dev'
Requires-Dist: tox-direct ; extra == 'dev'
Requires-Dist: types-mock ; extra == 'dev'
